greetings/__init__.py
greetings/greetings.py
greetings_package-0.1.0.dist-info/LICENSE
greetings_package-0.1.0.dist-info/METADATA
greetings_package-0.1.0.dist-info/WHEEL
greetings_package-0.1.0.dist-info/top_level.txt
greetings_package-0.1.0.dist-info/RECORD
